h5_validator/__init__.py
h5_validator/cli.py
h5_validator/matcher.py
h5_validator/schema.py
h5_validator/validator.py
h5_validator/schemas/bulk_read_fast5.yaml
h5_validator/schemas/multi_read_fast5.yaml
h5_validator/schemas/single_read_fast5.yaml
ont_h5_validator-2.0.1.dist-info/METADATA
ont_h5_validator-2.0.1.dist-info/RECORD
ont_h5_validator-2.0.1.dist-info/WHEEL
ont_h5_validator-2.0.1.dist-info/entry_points.txt
ont_h5_validator-2.0.1.dist-info/top_level.txt
ont_h5_validator-2.0.1.dist-info/zip-safe
