Metadata-Version: 2.1
Name: ont-h5-validator
Version: 2.0.1
Summary: Hdf5 validator package
Home-page: https://nanoporetech.com
Author: Oxford Nanopore Technologies Ltd
Author-email: info@nanoporetech.com
License: UNKNOWN
Platform: UNKNOWN
Requires-Dist: numpy
Requires-Dist: h5py
Requires-Dist: PyYAML (>=3.11)
